{
  "values": {
    "name": [
      "историскa"
    ]
  },
  "bibliography": "",
  "dateInspection": "12.12.2024",
  "currentData": {
    "physicalCondition": {
      "exterior": {
        "condition": "добра"
      },
      "interior": {
        "condition": "добра"
      }
    },
    "authenticity": {
      "exterior": {
        "condition": "добра"
      },
      "interior": {}
    }
  },
  "inspectionBy": "Тим 2",
  "code": "MNVE04",
  "order": 55,
  "photo": "/media/mnve04/mnve04_01.jpg",
  "basicData": {
    "coordinates": "{\"type\":\"Point\",\"coordinates\":[21.7775313,41.7175219]}",
    "address": {
      "city": "Велес"
    },
    "originalPurpose": {
      "type": [
        "јавен"
      ]
    },
    "todayPurpose": {
      "type": [
        "комерцијален/деловен"
      ]
    },
    "protectionStatus": {},
    "architect": "Крат В. Павле"
  }
}
